herobiz/__init__.py
herobiz/apps.py
herobiz/sitemaps.py
herobiz/urls.py
herobiz/views.py
herobiz/migrations/__init__.py
herobiz/static/herobiz/css/main.css
herobiz/static/herobiz/css/variables-blue.css
herobiz/static/herobiz/css/variables-green.css
herobiz/static/herobiz/css/variables-orange.css
herobiz/static/herobiz/css/variables-pink.css
herobiz/static/herobiz/css/variables-purple.css
herobiz/static/herobiz/css/variables-red.css
herobiz/static/herobiz/css/variables.css
herobiz/static/herobiz/img/about-bg.png
herobiz/static/herobiz/img/faq.jpg
herobiz/static/herobiz/img/hero-bg.png
herobiz/static/herobiz/img/onfocus-content-bg.jpg
herobiz/static/herobiz/img/pricing-bg.jpg
herobiz/static/herobiz/js/main.js
herobiz/static/herobiz/scss/_blog.scss
herobiz/static/herobiz/scss/_footer.scss
herobiz/static/herobiz/scss/_general.scss
herobiz/static/herobiz/scss/_header.scss
herobiz/static/herobiz/scss/_index.scss
herobiz/static/herobiz/scss/_nav.scss
herobiz/static/herobiz/scss/_portfolio-details.scss
herobiz/static/herobiz/scss/main.scss
herobiz/static/herobiz/scss/variables-blue.css
herobiz/static/herobiz/scss/variables-green.css
herobiz/static/herobiz/scss/variables-orange.css
herobiz/static/herobiz/scss/variables-pink.css
herobiz/static/herobiz/scss/variables-purple.css
herobiz/static/herobiz/scss/variables-red.css
herobiz/static/herobiz/scss/variables.css
herobiz/static/herobiz/scss/blog/_comments.scss
herobiz/static/herobiz/scss/blog/_details.scss
herobiz/static/herobiz/scss/blog/_pagination.scss
herobiz/static/herobiz/scss/blog/_posts-list.scss
herobiz/static/herobiz/scss/blog/_sidebar.scss
herobiz/static/herobiz/scss/index/_about.scss
herobiz/static/herobiz/scss/index/_clients.scss
herobiz/static/herobiz/scss/index/_contact.scss
herobiz/static/herobiz/scss/index/_cta.scss
herobiz/static/herobiz/scss/index/_faq.scss
herobiz/static/herobiz/scss/index/_featured-services.scss
herobiz/static/herobiz/scss/index/_features.scss
django_herobiz_dental-5.0.13.dist-info/WHEEL
django_herobiz_dental-5.0.13.dist-info/METADATA
django_herobiz_dental-5.0.13.dist-info/RECORD
