Metadata-Version: 2.3
Name: django_herobiz_dental
Version: 5.0.13
Summary: Demiansoft template(herobiz)
Requires-Python: >=3.6
Requires-Dist: Django>=4.2.11
Requires-Dist: shared_lib_ds>=1.3.3
